fast_csv_loader/__init__.py
fast_csv_loader/csv_loader.py
fast_csv_loader-2.0.0.dist-info/METADATA
fast_csv_loader-2.0.0.dist-info/WHEEL
fast_csv_loader-2.0.0.dist-info/licenses/LICENSE
fast_csv_loader-2.0.0.dist-info/RECORD
