Metadata-Version: 2.4
Name: fast_csv_loader
Version: 2.0.0
Summary: A fast and memory efficient way to load large CSV files (Timeseries data) into Pandas
Project-URL: Homepage, https://github.com/BennyThadikaran/fast_csv_loader
Project-URL: Bug Tracker, https://github.com/BennyThadikaran/fast_csv_loader/issues
Author: Benny Thadikaran
License-File: LICENSE
Keywords: csv-loader,csv-reader,memory-efficient,pandas-dataframe,python3
Classifier: Intended Audience :: Developers
Classifier: License :: OSI Approved :: GNU General Public License v3 (GPLv3)
Classifier: Natural Language :: English
Classifier: Operating System :: OS Independent
Classifier: Programming Language :: Python :: 3 :: Only
Classifier: Topic :: Software Development :: Libraries :: Python Modules
Requires-Python: >=3.8
Requires-Dist: pandas<3,>=2
Provides-Extra: docs
Requires-Dist: furo==2024.8.6; extra == 'docs'
Requires-Dist: sphinx==8.1.3; extra == 'docs'
